LICENSE.txt
MANIFEST.in
README.rst
setup.cfg
setup.py
es_commands/__init__.py
es_commands/base.py
es_commands/cat_api.py
es_commands/cluster_api.py
es_commands/junk.py
es_commands/node_api.py
es_commands/tes.py
tes.egg-info/PKG-INFO
tes.egg-info/SOURCES.txt
tes.egg-info/dependency_links.txt
tes.egg-info/entry_points.txt
tes.egg-info/requires.txt
tes.egg-info/top_level.txt