Metadata-Version: 1.1
Name: tes
Version: 1.1.1
Summary: Tool for Elasticsearch
Home-page: https://github.com/deeshugupta/tes
Author: Deepanshu Gupta
Author-email: gupta.deeshu@gmail.com
License: GNU General Public License v3.0
Download-URL: https://github.com/deeshugupta/tes/archive/v1.1.1.tar.gz
Keywords: tes elasticsearch Elasticsearch
Platform: UNKNOWN
Classifier: Development Status :: 4 - Beta
Classifier: Intended Audience :: Developers
Classifier: Topic :: System :: Monitoring
Classifier: License :: OSI Approved :: GNU General Public License v3 (GPLv3)
Classifier: Programming Language :: Python :: 2.7
